README.md
setup.py
mo_flex_sdk/__init__.py
mo_flex_sdk/sdk.py
mo_flex_sdk.egg-info/PKG-INFO
mo_flex_sdk.egg-info/SOURCES.txt
mo_flex_sdk.egg-info/dependency_links.txt
mo_flex_sdk.egg-info/requires.txt
mo_flex_sdk.egg-info/top_level.txt