Metadata-Version: 2.1
Name: mo-flex-sdk
Version: 0.0.1
Summary: Rhm
Home-page: UNKNOWN
Author: liuhandong
Author-email: 
License: UNKNOWN
Keywords: python,flink,arg,toml,windows,linux
Platform: UNKNOWN
Classifier: Development Status :: 1 - Planning
Classifier: Intended Audience :: Developers
Classifier: Programming Language :: Python :: 3
Classifier: Operating System :: Microsoft :: Windows
Classifier: Operating System :: Unix
